topsis/__init__.py
topsis/__main__.py
Topsis_JatinGoyal_102003307-1.0.0.dist-info/LICENSE
Topsis_JatinGoyal_102003307-1.0.0.dist-info/METADATA
Topsis_JatinGoyal_102003307-1.0.0.dist-info/WHEEL
Topsis_JatinGoyal_102003307-1.0.0.dist-info/entry_points.txt
Topsis_JatinGoyal_102003307-1.0.0.dist-info/top_level.txt
Topsis_JatinGoyal_102003307-1.0.0.dist-info/RECORD
