Metadata-Version: 2.1
Name: Topsis-JatinGoyal-102003307
Version: 1.0.0
Summary: A Python package implementing TOPSIS technique.
Home-page: https://github.com/jating05/topsisImplementation
Author: Jatin Goyal
Author-email: jatingoyal452002@gmail.com
License: MIT
Classifier: License :: OSI Approved :: MIT License
Classifier: Programming Language :: Python :: 3
Classifier: Programming Language :: Python :: 3.7
License-File: LICENSE
Requires-Dist: numpy
Requires-Dist: pandas
